Workbook

Sheet ANSWER-16,17,18
A1: Row Labels | B1: Sum of TOTAL SALES
A2: Laptop | B2: 225000
A3: Mobile | B3: 135000
A4: Tablet | B4: 54000
A5: Grand Total | B5: 414000
A7: ANSWER-16
A15: Row Labels | B15: Sum of TOTAL SALES
A16: East | B16: 54000
A17: North | B17: 150000
A18: South | B18: 165000 | G18: ANSWER-18
A19: West | B19: 45000
A20: Grand Total | B20: 414000
B22: ANSWER-17

Sheet Sales_Data
A1: Order_ID | B1: Region | C1: Salesperson | D1: Product | E1: Quantity | F1: Unit_Price | G1: Sales_Date | H1: TOTAL SALES | I1: GST AMOUNT | J1: FINAL AMOUNT | K1: GRAND TOTAL | L1: COUNT TOTAL ORDER | M1: REGION | N1: TTOAL SALES | O1: HIGH/LOW QTY | P1: MAX FINAL AMOUNT | Q1: MIN FINAL AMOUNT | R1: MONTH NAME | U1: LEFT FUNCATION | V1: COUNT LAPTOP REGION
A2: 301 | B2: North | C2: Amit | D2: Laptop | E2: 2 | F2: 45000 | G2: 05-01-2025 | H2: =E2*F2 -> 90000 | I2: =H2*VLOOKUP(D2,Product_Master!$A$2:$C$4,3,0)/100 -> 16200 | J2: =H2+I2 -> 106200 | K2: =SUM(J2:J7) -> 477180 | L2: =COUNTA(A2:A7) -> 6 | M2: NORTH | N2: =SUMIF($B$2:$B$7,M2,$H$2:$H$7) -> 150000 | O2: =IF(E2>3,"HIGH","LOW") -> LOW | P2: =MAX(J2:J7) -> 106200 | Q2: =MIN(J2:J7) -> 53100 | R2: =TEXT(G2,"MMMM") -> January | U2: =LEFT(C2,2) -> Am | V2: =COUNTIFS(B2:B7,"North",D2:D7,"Laptop") -> 1
A3: 302 | B3: South | C3: Riya | D3: Mobile | E3: 5 | F3: 15000 | G3: 07-01-2025 | H3: =E3*F3 -> 75000 | I3: =H3*VLOOKUP(D3,Product_Master!$A$2:$C$4,3,0)/100 -> 9000 | J3: =H3+I3 -> 84000 | M3: SOUTH | N3: =SUMIF($B$2:$B$7,M3,$H$2:$H$7) -> 165000 | O3: =IF(E3>3,"HIGH","LOW") -> HIGH | R3: =TEXT(G3,"MMMM") -> January | U3: =LEFT(C3,2) -> Ri
A4: 303 | B4: East | C4: Kunal | D4: Tablet | E4: 3 | F4: 18000 | G4: 10-01-2025 | H4: =E4*F4 -> 54000 | I4: =H4*VLOOKUP(D4,Product_Master!$A$2:$C$4,3,0)/100 -> 6480 | J4: =H4+I4 -> 60480 | M4: EAST | N4: =SUMIF($B$2:$B$7,M4,$H$2:$H$7) -> 54000 | O4: =IF(E4>3,"HIGH","LOW") -> LOW | R4: =TEXT(G4,"MMMM") -> January | U4: =LEFT(C4,2) -> Ku
A5: 304 | B5: West | C5: Neha | D5: Laptop | E5: 1 | F5: 45000 | G5: 12-01-2025 | H5: =E5*F5 -> 45000 | I5: =H5*VLOOKUP(D5,Product_Master!$A$2:$C$4,3,0)/100 -> 8100 | J5: =H5+I5 -> 53100 | M5: WEST | N5: =SUMIF($B$2:$B$7,M5,$H$2:$H$7) -> 45000 | O5: =IF(E5>3,"HIGH","LOW") -> LOW | R5: =TEXT(G5,"MMMM") -> January | U5: =LEFT(C5,2) -> Ne
A6: 305 | B6: North | C6: Amit | D6: Mobile | E6: 4 | F6: 15000 | G6: 15-01-2025 | H6: =E6*F6 -> 60000 | I6: =H6*VLOOKUP(D6,Product_Master!$A$2:$C$4,3,0)/100 -> 7200 | J6: =H6+I6 -> 67200 | O6: =IF(E6>3,"HIGH","LOW") -> HIGH | R6: =TEXT(G6,"MMMM") -> January | U6: =LEFT(C6,2) -> Am
A7: 306 | B7: South | C7: Riya | D7: Laptop | E7: 2 | F7: 45000 | G7: 18-01-2025 | H7: =E7*F7 -> 90000 | I7: =H7*VLOOKUP(D7,Product_Master!$A$2:$C$4,3,0)/100 -> 16200 | J7: =H7+I7 -> 106200 | O7: =IF(E7>3,"HIGH","LOW") -> LOW | R7: =TEXT(G7,"MMMM") -> January | U7: =LEFT(C7,2) -> Ri
H8: ANSWER-1 | I8: ANSWER-2 | J8: ANSWER-3,24 | K8: ANSWER-4 | L8: ANSWER-5 | M8: ANSWER-6 | O8: ANSWER-7 | P8: ANSWER-8 | R8: ANSWER-9 | S8: ANSWER-11 | T8: ANSWER-10 | U8: ANSWER-23 | V8: ANSWER-26 | W8: ANSWER-27
C14: Product | D14: Quantity
C15: Laptop | D15: 2 | F15: FREES TOP ROW
C16: Mobile | D16: 5
C17: Tablet | D17: 3
C18: Laptop | D18: 1
C19: Mobile | D19: 4
C20: Laptop | D20: 2
C21: ANSWER-25 | F21: ANSWER-29

Sheet Product_Master
A1: Product | B1: Category | C1: GST_% | D1: DUPLICATE
A2: Laptop | B2: Electronics | C2: 18
A3: Mobile | B3: Electronics | C3: 12
A4: Tablet | B4: Electronics | C4: 12
D5: ANSWER-28

Sheet ANSWER-19
A1: Row Labels | B1: Sum of Excel
A2: Arjun | B2: 72
A3: Pooja | B3: 94
A4: Rahul | B4: 85
A5: Sneha | B5: 90
A6: Vikas | B6: 58
A7: Grand Total | B7: 399
D19: ANSWER-19

Sheet Student_Marks
A1: Student_ID | B1: Name | C1: Maths | D1: Statistics | E1: Excel | F1: Attendance_% | G1: AVG MARKS | H1: FIND TOPPER | I1: ATTENDANCE | J1: ELIGIBLE /NOT | K1: MEDIAN | M1: CONCAT
A2: 1 | B2: Rahul | C2: 78 | D2: 82 | E2: 85 | F2: 92 | G2: =AVERAGE(C2:E2) -> 81.666667 | I2: =COUNTIF(F2:F6,">90") -> 3 | J2: =IF(F2>=85,"ELIGIBLE","NOT ELIGIBLE") -> ELIGIBLE | K2: =MEDIAN(D2:D6) -> 82 | M2: =_xlfn.CONCAT(A2,"-",B2) -> 1-Rahul
A3: 2 | B3: Sneha | C3: 88 | D3: 91 | E3: 90 | F3: 96 | G3: =AVERAGE(C3:E3) -> 89.666667 | J3: =IF(F3>=85,"ELIGIBLE","NOT ELIGIBLE") -> ELIGIBLE | K3: =MEDIAN(D3:D7) -> 79.5 | M3: =_xlfn.CONCAT(A3,"-",B3) -> 2-Sneha
A4: 3 | B4: Arjun | C4: 65 | D4: 70 | E4: 72 | F4: 85 | G4: =AVERAGE(C4:E4) -> 69 | J4: =IF(F4>=85,"ELIGIBLE","NOT ELIGIBLE") -> ELIGIBLE | K4: =MEDIAN(D4:D8) -> 70 | M4: =_xlfn.CONCAT(A4,"-",B4) -> 3-Arjun
A5: 4 | B5: Pooja | C5: 92 | D5: 89 | E5: 94 | F5: 98 | G5: =AVERAGE(C5:E5) -> 91.666667 | J5: =IF(F5>=85,"ELIGIBLE","NOT ELIGIBLE") -> ELIGIBLE | K5: =MEDIAN(D5:D9) -> 74.5 | M5: =_xlfn.CONCAT(A5,"-",B5) -> 4-Pooja
A6: 5 | B6: Vikas | C6: 55 | D6: 60 | E6: 58 | F6: 80 | G6: =AVERAGE(C6:E6) -> 57.666667 | J6: =IF(F6>=85,"ELIGIBLE","NOT ELIGIBLE") -> NOT ELIGIBLE | K6: =MEDIAN(D6:D10) -> 60 | M6: =_xlfn.CONCAT(A6,"-",B6) -> 5-Vikas
G7: ANSWER-12 | H7: ANSWER-13 | I7: ANSWER-14 | J7: ANSWER-15 | K7: ANSWER-20 | L7: ANSWER-21 | M7: ANSWER-22
F14: ANSWER-30

Sheet Questions
A1: 1 | B1: Calculate Total Sales for each order (Quantity × Unit_Price). | I1: 2
A2: 2 | B2: Calculate GST Amount using VLOOKUP from Product_Master. | I2: 2
A3: 3 | B3: Find Final Amount payable (Total Sales + GST). | I3: 2
A4: 4 | B4: Find Grand Total of Final Amount. | I4: 2
A5: 5 | B5: Count total number of orders using COUNTA. | I5: 2
A6: 6 | B6: Find Region-wise total sales using SUMIF. | I6: 2
A7: 7 | B7: Use IF to classify Quantity as High (>3) or Low (<=3). | I7: 2
A8: 8 | B8: Find the maximum and minimum Final Amount. | I8: 2
A9: 9 | B9: Extract month name from Sales_Date. | I9: 2
A10: 10 | B10: Sort Sales_Data by Final Amount (Descending). | I10: 2
A11: 11 | B11: Use INDEX-MATCH to fetch Product Category. | I11: 2
A12: 12 | B12: Calculate average marks of each student. | I12: 2
... A30: 30 | B30: Protect the Student_Marks sheet. | I30: 2
I31: 60
